[{"timestamp":"2025-10-04T01:04:16.141Z","count":0,"uniques":0},{"timestamp":"2025-10-05T01:14:37.029Z","count":0,"uniques":0},{"timestamp":"2025-10-06T01:09:21.760Z","count":0,"uniques":0},{"timestamp":"2025-10-07T01:07:55.422Z","count":0,"uniques":0},{"timestamp":"2025-10-08T01:07:38.839Z","count":0,"uniques":0},{"timestamp":"2025-10-09T01:08:41.314Z","count":0,"uniques":0},{"timestamp":"2025-10-10T01:08:32.419Z","count":0,"uniques":0},{"timestamp":"2025-10-11T01:05:47.319Z","count":0,"uniques":0},{"timestamp":"2025-10-12T01:11:52.580Z","count":0,"uniques":0},{"timestamp":"2025-10-13T01:13:23.705Z","count":0,"uniques":0},{"timestamp":"2025-10-14T01:08:35.066Z","count":0,"uniques":0},{"timestamp":"2025-10-15T01:10:20.216Z","count":0,"uniques":0},{"timestamp":"2025-10-16T01:09:58.685Z","count":0,"uniques":0},{"timestamp":"2025-10-17T01:09:37.321Z","count":0,"uniques":0},{"timestamp":"2025-10-18T01:46:05.682Z","count":0,"uniques":0},{"timestamp":"2025-10-19T01:17:49.560Z","count":0,"uniques":0},{"timestamp":"2025-10-20T01:15:07.573Z","count":0,"uniques":0},{"timestamp":"2025-10-21T01:12:07.053Z","count":0,"uniques":0},{"timestamp":"2025-10-22T01:13:23.774Z","count":0,"uniques":0},{"timestamp":"2025-10-23T01:11:03.438Z","count":0,"uniques":0},{"timestamp":"2025-10-24T01:07:39.744Z","count":0,"uniques":0},{"timestamp":"2025-10-25T01:08:58.819Z","count":0,"uniques":0},{"timestamp":"2025-10-26T01:16:00.512Z","count":0,"uniques":0},{"timestamp":"2025-10-27T01:17:13.856Z","count":0,"uniques":0},{"timestamp":"2025-10-28T01:09:54.049Z","count":0,"uniques":0},{"timestamp":"2025-10-29T01:15:05.028Z","count":0,"uniques":0},{"timestamp":"2025-10-30T01:14:23.164Z","count":0,"uniques":0},{"timestamp":"2025-10-31T01:12:22.076Z","count":0,"uniques":0},{"timestamp":"2025-11-01T01:16:21.602Z","count":0,"uniques":0},{"timestamp":"2025-11-02T01:17:05.676Z","count":0,"uniques":0},{"timestamp":"2025-11-03T01:15:48.187Z","count":0,"uniques":0}]
