[{"timestamp":"2022-07-27T01:15:34.717Z","count":0,"uniques":0},{"timestamp":"2022-07-28T01:08:48.070Z","count":0,"uniques":0},{"timestamp":"2022-07-29T01:13:13.003Z","count":0,"uniques":0},{"timestamp":"2022-07-30T01:06:29.087Z","count":0,"uniques":0},{"timestamp":"2022-07-31T01:23:38.922Z","count":0,"uniques":0},{"timestamp":"2022-08-01T00:00:00.000Z","count":1,"uniques":1},{"timestamp":"2022-08-02T01:19:53.652Z","count":0,"uniques":0},{"timestamp":"2022-08-03T01:16:39.257Z","count":0,"uniques":0}]
