[{"timestamp":"2023-05-05T00:50:34.326Z","count":0,"uniques":0},{"timestamp":"2023-05-06T00:51:00.374Z","count":0,"uniques":0},{"timestamp":"2023-05-07T00:58:01.026Z","count":0,"uniques":0},{"timestamp":"2023-05-08T00:52:57.003Z","count":0,"uniques":0},{"timestamp":"2023-05-09T00:55:11.950Z","count":0,"uniques":0},{"timestamp":"2023-05-10T00:53:46.884Z","count":0,"uniques":0},{"timestamp":"2023-05-11T00:54:38.636Z","count":0,"uniques":0},{"timestamp":"2023-05-12T00:54:01.872Z","count":0,"uniques":0}]
