[{"timestamp":"2023-09-04T00:46:37.916Z","count":0,"uniques":0},{"timestamp":"2023-09-05T00:44:42.205Z","count":0,"uniques":0},{"timestamp":"2023-09-06T00:45:48.534Z","count":0,"uniques":0},{"timestamp":"2023-09-07T00:45:12.002Z","count":0,"uniques":0},{"timestamp":"2023-09-08T00:45:26.984Z","count":0,"uniques":0},{"timestamp":"2023-09-09T00:43:58.663Z","count":0,"uniques":0},{"timestamp":"2023-09-10T00:49:19.156Z","count":0,"uniques":0},{"timestamp":"2023-09-11T00:46:19.670Z","count":0,"uniques":0}]
