[{"timestamp":"2024-09-01T01:09:07.953Z","count":0,"uniques":0},{"timestamp":"2024-09-02T01:00:36.763Z","count":0,"uniques":0},{"timestamp":"2024-09-03T00:58:51.156Z","count":0,"uniques":0},{"timestamp":"2024-09-04T00:59:53.102Z","count":0,"uniques":0},{"timestamp":"2024-09-05T00:59:39.444Z","count":0,"uniques":0},{"timestamp":"2024-09-06T00:59:36.593Z","count":0,"uniques":0},{"timestamp":"2024-09-07T00:58:29.094Z","count":0,"uniques":0},{"timestamp":"2024-09-08T01:04:35.556Z","count":0,"uniques":0}]
