[{"timestamp":"2023-07-17T01:11:32.196Z","count":0,"uniques":0},{"timestamp":"2023-07-18T00:00:00.000Z","count":1,"uniques":1},{"timestamp":"2023-07-19T02:03:04.757Z","count":0,"uniques":0},{"timestamp":"2023-07-20T00:59:43.736Z","count":0,"uniques":0},{"timestamp":"2023-07-21T00:59:40.039Z","count":0,"uniques":0},{"timestamp":"2023-07-22T00:59:32.903Z","count":0,"uniques":0},{"timestamp":"2023-07-23T01:03:27.152Z","count":0,"uniques":0},{"timestamp":"2023-07-24T01:00:10.342Z","count":0,"uniques":0}]
