[{"timestamp":"2020-08-01T02:15:24.867Z","count":0,"uniques":0},{"timestamp":"2020-09-01T02:15:24.867Z","count":0,"uniques":0},{"timestamp":"2020-10-01T02:15:24.867Z","count":0,"uniques":0},{"timestamp":"2020-11-01T02:15:24.867Z","count":0,"uniques":0},{"timestamp":"2020-12-01T02:15:24.867Z","count":0,"uniques":0},{"timestamp":"2021-01-01T02:15:24.867Z","count":0,"uniques":0},{"timestamp":"2021-02-01T02:15:24.867Z","count":0,"uniques":0},{"timestamp":"2021-03-01T02:15:24.867Z","count":0,"uniques":0},{"timestamp":"2021-04-01T02:15:24.867Z","count":0,"uniques":0},{"timestamp":"2021-05-01T02:15:24.867Z","count":0,"uniques":0},{"timestamp":"2021-06-01T18:12:36.521Z","count":212,"uniques":107},{"timestamp":"2021-07-01T18:11:46.665Z","count":187,"uniques":104},{"timestamp":"2021-08-01T18:11:38.299Z","count":275,"uniques":137},{"timestamp":"2021-09-01T18:12:12.495Z","count":240,"uniques":133},{"timestamp":"2021-10-01T18:12:23.149Z","count":364,"uniques":84},{"timestamp":"2021-11-01T18:13:58.600Z","count":196,"uniques":92},{"timestamp":"2021-12-01T18:14:24.006Z","count":202,"uniques":112},{"timestamp":"2022-01-01T18:13:10.785Z","count":230,"uniques":121},{"timestamp":"2022-02-01T18:14:32.810Z","count":338,"uniques":149},{"timestamp":"2022-03-01T18:15:23.014Z","count":453,"uniques":212},{"timestamp":"2022-04-01T18:16:04.586Z","count":568,"uniques":244},{"timestamp":"2022-05-01T18:15:36.606Z","count":417,"uniques":216},{"timestamp":"2022-06-01T18:16:28.171Z","count":331,"uniques":149},{"timestamp":"2022-07-01T12:22:50.799Z","count":298,"uniques":132},{"timestamp":"2022-08-01T18:17:54.369Z","count":244,"uniques":109},{"timestamp":"2022-09-01T18:20:37.796Z","count":324,"uniques":166},{"timestamp":"2022-10-01T18:15:58.327Z","count":364,"uniques":151},{"timestamp":"2022-11-01T18:14:28.993Z","count":296,"uniques":160},{"timestamp":"2022-12-01T18:12:47.904Z","count":326,"uniques":129},{"timestamp":"2023-01-01T18:14:41.296Z","count":324,"uniques":146},{"timestamp":"2023-02-01T18:17:18.997Z","count":281,"uniques":126},{"timestamp":"2023-03-01T18:13:03.483Z","count":297,"uniques":134},{"timestamp":"2023-04-01T18:11:30.688Z","count":306,"uniques":108},{"timestamp":"2023-05-01T18:12:54.504Z","count":204,"uniques":95},{"timestamp":"2023-06-01T18:14:07.833Z","count":219,"uniques":100},{"timestamp":"2023-07-01T18:12:40.752Z","count":324,"uniques":145},{"timestamp":"2023-08-01T18:13:32.182Z","count":236,"uniques":110},{"timestamp":"2023-09-01T18:12:30.024Z","count":349,"uniques":109},{"timestamp":"2023-10-01T12:19:42.448Z","count":344,"uniques":175},{"timestamp":"2023-11-01T18:13:57.651Z","count":421,"uniques":185},{"timestamp":"2023-12-01T18:12:52.641Z","count":353,"uniques":144},{"timestamp":"2024-01-01T18:13:00.433Z","count":717,"uniques":188},{"timestamp":"2024-02-01T18:13:09.062Z","count":701,"uniques":268},{"timestamp":"2024-03-01T22:53:35.495Z","count":296,"uniques":138},{"timestamp":"2024-04-01T18:14:18.637Z","count":460,"uniques":158},{"timestamp":"2024-05-01T18:16:27.718Z","count":417,"uniques":173},{"timestamp":"2024-06-01T18:23:31.851Z","count":329,"uniques":154},{"timestamp":"2024-07-01T18:16:18.210Z","count":592,"uniques":194},{"timestamp":"2024-08-01T18:16:10.735Z","count":391,"uniques":147},{"timestamp":"2024-09-01T18:18:07.323Z","count":584,"uniques":190},{"timestamp":"2024-10-01T18:18:50.840Z","count":378,"uniques":199},{"timestamp":"2024-11-01T18:18:01.574Z","count":220,"uniques":130},{"timestamp":"2024-12-01T18:17:45.008Z","count":332,"uniques":154},{"timestamp":"2025-01-01T18:18:14.668Z","count":356,"uniques":248},{"timestamp":"2025-02-01T18:19:08.190Z","count":500,"uniques":388},{"timestamp":"2025-03-01T18:20:37.395Z","count":357,"uniques":183},{"timestamp":"2025-04-01T18:19:28.439Z","count":311,"uniques":190},{"timestamp":"2025-05-01T18:19:18.524Z","count":503,"uniques":285},{"timestamp":"2025-06-01T18:24:23.862Z","count":297,"uniques":196},{"timestamp":"2025-07-01T01:15:44.716Z","count":455,"uniques":260},{"timestamp":"2025-08-01T01:15:44.716Z","count":706,"uniques":419}]
