[{"timestamp":"2023-01-20T00:00:00.000Z","count":30,"uniques":18},{"timestamp":"2023-01-21T00:00:00.000Z","count":67,"uniques":28},{"timestamp":"2023-01-22T00:00:00.000Z","count":270,"uniques":131},{"timestamp":"2023-01-23T00:00:00.000Z","count":102,"uniques":49},{"timestamp":"2023-01-24T00:00:00.000Z","count":109,"uniques":42},{"timestamp":"2023-01-25T00:00:00.000Z","count":146,"uniques":76},{"timestamp":"2023-01-26T00:00:00.000Z","count":73,"uniques":28},{"timestamp":"2023-01-27T00:00:00.000Z","count":13,"uniques":6}]
